yourbooks/__init__.py
yourbooks/__main__.py
yourbooks/books.py
yourbooks/config.py
yourbooks/exceptions.py
yourbooks/user.py
yourbooks-0.1.2.dist-info/LICENSE
yourbooks-0.1.2.dist-info/WHEEL
yourbooks-0.1.2.dist-info/METADATA
yourbooks-0.1.2.dist-info/RECORD
