Metadata-Version: 2.1
Name: yourbooks
Version: 0.1.2
Summary: CLI for a Books/Reading List FastAPI application
Keywords: books,reading,Google Books API,authors,FastAPI
Author: Ben Griffith
Requires-Python: >=3.9
Classifier: License :: OSI Approved :: MIT License
Requires-Dist: typer
Requires-Dist: fastapi
Requires-Dist: requests
Project-URL: Source, https://github.com/bengriffith/book-api-cli
